pictorial/__init__.py
pictorial/aggregate.py
pictorial/utility.py
pictorial/core/__init__.py
pictorial/core/bar.py
pictorial/core/box.py
pictorial/core/corr.py
pictorial/core/subplots.py
pictorial/testing/__init__.py
pictorial/testing/data.py
pictorial-2021.12.1.dist-info/LICENSE
pictorial-2021.12.1.dist-info/METADATA
pictorial-2021.12.1.dist-info/WHEEL
pictorial-2021.12.1.dist-info/top_level.txt
pictorial-2021.12.1.dist-info/RECORD
