Metadata-Version: 2.1
Name: pictorial
Version: 2021.12.1
Summary: Python package for plotting
Home-page: https://github.com/tahini-dev/pictorial
Author: tahini-dev
Author-email: tahini.dev@gmail.com
License: UNKNOWN
Platform: UNKNOWN
Requires-Python: >=3.7
License-File: LICENSE
Requires-Dist: pandas (>=1.1.0)
Requires-Dist: plotly (>=5.5.0)
Requires-Dist: numpy (>=1.12.5)
Provides-Extra: all
